gygo42/__init__.py
gygo42/gygo42.py
gygo42-7.8.7.dist-info/METADATA
gygo42-7.8.7.dist-info/WHEEL
gygo42-7.8.7.dist-info/top_level.txt
gygo42-7.8.7.dist-info/RECORD
