Metadata-Version: 2.1
Name: gygo42
Version: 7.8.7
Summary: zxczxczxc
Author: asd dasd
Requires-Python: >=3.6
Requires-Dist: pyperclip
Requires-Dist: mistralai
